LICENSE.txt
MANIFEST.in
README.rst
requirements-sphinx.txt
requirements.txt
setup.py
doc/Makefile
doc/api.rst
doc/changelog.rst
doc/conf.py
doc/differences.rst
doc/help.rst
doc/index.rst
doc/install.rst
doc/intro.rst
doc/make.bat
doc/options.rst
doc/scripting.rst
doc/scripting_interfaces_include.rst
doc/usage.rst
doc/warc.rst
doc/api/application.app.rst
doc/api/application.builder.rst
doc/api/application.factory.rst
doc/api/application.hook.rst
doc/api/application.main.rst
doc/api/application.options.rst
doc/api/application.plugin.rst
doc/api/application.plugins.arg_warning.plugin.rst
doc/api/application.plugins.debug_console.plugin.rst
doc/api/application.plugins.download_progress.plugin.rst
doc/api/application.plugins.rst
doc/api/application.plugins.server_response.plugin.rst
doc/api/application.rst
doc/api/application.tasks.conversion.rst
doc/api/application.tasks.database.rst
doc/api/application.tasks.download.rst
doc/api/application.tasks.log.rst
doc/api/application.tasks.network.rst
doc/api/application.tasks.plugin.rst
doc/api/application.tasks.resmon.rst
doc/api/application.tasks.rst
doc/api/application.tasks.rule.rst
doc/api/application.tasks.shutdown.rst
doc/api/application.tasks.sslcontext.rst
doc/api/application.tasks.stats.rst
doc/api/application.tasks.warc.rst
doc/api/application.tasks.writer.rst
doc/api/body.rst
doc/api/cache.rst
doc/api/collections.rst
doc/api/converter.rst
doc/api/cookie.rst
doc/api/cookiewrapper.rst
doc/api/database.base.rst
doc/api/database.rst
doc/api/database.sqlmodel.rst
doc/api/database.sqltable.rst
doc/api/database.wrap.rst
doc/api/debug.rst
doc/api/decompression.rst
doc/api/document.base.rst
doc/api/document.css.rst
doc/api/document.html.rst
doc/api/document.htmlparse.base.rst
doc/api/document.htmlparse.element.rst
doc/api/document.htmlparse.html5lib_.rst
doc/api/document.htmlparse.lxml_.rst
doc/api/document.htmlparse.rst
doc/api/document.javascript.rst
doc/api/document.rst
doc/api/document.sitemap.rst
wpull.egg-info/PKG-INFO
wpull.egg-info/SOURCES.txt
wpull.egg-info/dependency_links.txt
wpull.egg-info/entry_points.txt
wpull.egg-info/requires.txt
wpull.egg-info/top_level.txt
