Metadata-Version: 1.1
Name: wpull
Version: 2.0
Summary: Wget-compatible web downloader and crawler.
Home-page: https://github.com/chfoo/wpull
Author: Christopher Foo
Author-email: chris.foo@gmail.com
License: UNKNOWN
Platform: UNKNOWN
Classifier: Development Status :: 5 - Production/Stable
Classifier: License :: OSI Approved :: GNU General Public License v3 (GPLv3)
Classifier: Programming Language :: Python :: 3
Classifier: Programming Language :: Python :: 3.4
Classifier: Programming Language :: Python :: 3.5
Classifier: Topic :: Internet :: File Transfer Protocol (FTP)
Classifier: Topic :: Internet :: WWW/HTTP
Classifier: Topic :: System :: Archiving
